cloud_cartographer/__init__.py
cloud_cartographer-0.0.5.dist-info/licenses/LICENSE.txt
cloud_cartographer-0.0.5.dist-info/METADATA
cloud_cartographer-0.0.5.dist-info/WHEEL
cloud_cartographer-0.0.5.dist-info/entry_points.txt
cloud_cartographer-0.0.5.dist-info/top_level.txt
cloud_cartographer-0.0.5.dist-info/RECORD
