Metadata-Version: 2.4
Name: cloud-cartographer
Version: 0.0.5
Summary: AWS Cloudformation mapping tool to expose resources managed by Cloudformation and dependencies between stacks via their export/import relations.
Author-email: Vincent Van Gestel <vincent@vvgit.be>
Maintainer-email: Vincent Van Gestel <vincent@vvgit.be>
License: Copyright (c) 2025 vvgIT
Project-URL: Homepage, https://github.com/vvangestel/cloud-cartographer
Project-URL: Bug Reports, https://github.com/vvangestel/cloud-cartographer/issues
Project-URL: Source, https://github.com/vvangestel/cloud-cartographer
Keywords: aws,cloud,graph,data visualization,dataviz,mapping,dependency
Classifier: Development Status :: 3 - Alpha
Classifier: Intended Audience :: Developers
Classifier: Topic :: Software Development :: Documentation
Classifier: License :: OSI Approved :: MIT License
Classifier: Programming Language :: Python :: 3
Classifier: Programming Language :: Python :: 3.9
Classifier: Programming Language :: Python :: 3.10
Classifier: Programming Language :: Python :: 3.11
Classifier: Programming Language :: Python :: 3.12
Classifier: Programming Language :: Python :: 3.13
Classifier: Programming Language :: Python :: 3 :: Only
Requires-Python: >=3.9
License-File: LICENSE.txt
Requires-Dist: boto3
Requires-Dist: py-markdown-table
Requires-Dist: pyyaml
Dynamic: license-file
